README.md
setup.cfg
setup.py
iot_plot.egg-info/PKG-INFO
iot_plot.egg-info/SOURCES.txt
iot_plot.egg-info/dependency_links.txt
iot_plot.egg-info/entry_points.txt
iot_plot.egg-info/requires.txt
iot_plot.egg-info/top_level.txt
lib/__init__.py
lib/mqttclient.py
lib/plotclient.py
lib/plotserver.py