Metadata-Version: 1.1
Name: iot-plot
Version: 0.6.1
Summary: Remote plotting library
Home-page: https://github.com/bboser/iot-plot
Author: Bernhard Boser
Author-email: boser@berkeley.edu
License: MIT
Keywords: plotting,micropython,MQTT
Platform: UNKNOWN
Classifier: Development Status :: 3 - Alpha
Classifier: Environment :: Console
Classifier: Intended Audience :: Developers
Classifier: License :: OSI Approved :: MIT License
Classifier: Natural Language :: English
Classifier: Programming Language :: Python
Classifier: Programming Language :: Python :: 3
Classifier: Topic :: Software Development :: Embedded Systems
Classifier: Topic :: Utilities
